{
    "sourceFile": "src/pages/Mosaic.jsx",
    "activeCommit": 0,
    "commits": [
        {
            "activePatchIndex": 2,
            "patches": [
                {
                    "date": 1765474407526,
                    "content": "Index: \n===================================================================\n--- \n+++ \n"
                },
                {
                    "date": 1769780497151,
                    "content": "Index: \n===================================================================\n--- \n+++ \n@@ -277,9 +277,9 @@\n \n   return (\n     <main className=\"mosaic-page\">\n       <header className=\"mosaic-header\">\n-        <h1 className=\"mosaic-title\">Mosaico Colaborativo</h1>\n+        <h1 className=\"mosaic-title\">Mosaico colaborativo de La Sagrada Família</h1>\n         <p className=\"mosaic-subtitle\">\n           Explora el mural en alta definición. Click para ver fotos originales.\n         </p>\n       </header>\n"
                },
                {
                    "date": 1769780798617,
                    "content": "Index: \n===================================================================\n--- \n+++ \n@@ -306,9 +306,9 @@\n         <h1 className=\"mosaic-title\">\n           Mosaico colaborativo de La Sagrada Família\n         </h1>\n         <p className=\"mosaic-subtitle\">\n-          Explora el mural en alta definición. Click para ver fotos originales.\n+          Explora el mural foto a foto. Haz click para ver cada una de sus fotos en alta definición.\n         </p>\n       </header>\n \n       <section className=\"mosaic-container\">\n"
                }
            ],
            "date": 1765474407526,
            "name": "Commit-0",
            "content": "// src/pages/Mosaic.jsx\nimport React, { useEffect, useState } from \"react\";\nimport \"./Mosaic.css\";\nimport MosaicComponent from \"../components/MosaicComponent\";\n\nexport default function Mosaic() {\n  const [theme, setTheme] = useState(\"day\");\n\n  // Tema automático coherente con la Home\n  useEffect(() => {\n    const hour = new Date().getHours();\n    if (hour >= 21 || hour < 6) setTheme(\"sunset\");\n    else setTheme(\"day\");\n  }, []);\n\n  useEffect(() => {\n    document.documentElement.setAttribute(\"data-theme\", theme);\n  }, [theme]);\n\n  return (\n    <main className=\"mosaic-page\">\n      <header className=\"mosaic-header\">\n        <h1 className=\"mosaic-title\">Mosaico colaborativo</h1>\n        <p className=\"mosaic-subtitle\">\n          Visualiza en tiempo real la construcción del mosaico global.\n        </p>\n      </header>\n\n      <section className=\"mosaic-container\">\n        <MosaicComponent />\n      </section>\n    </main>\n  );\n}\n"
        }
    ]
}